Metadata-Version: 2.1
Name: instant-dm
Version: 1.0
Summary: an automation software 
Author: jack
Author-email: kinginjack@gmail.com
License: GPL-3.0
Platform: UNKNOWN
Requires-Python: >=3.8
